whatdat/__init__.py
whatdat-0.1.0.dist-info/METADATA
whatdat-0.1.0.dist-info/WHEEL
whatdat-0.1.0.dist-info/top_level.txt
whatdat-0.1.0.dist-info/RECORD
